autogen_core/__init__.py
autogen_core/_agent.py
autogen_core/_agent_id.py
autogen_core/_agent_instantiation.py
autogen_core/_agent_metadata.py
autogen_core/_agent_proxy.py
autogen_core/_agent_runtime.py
autogen_core/_agent_type.py
autogen_core/_base_agent.py
autogen_core/_cache_store.py
autogen_core/_cancellation_token.py
autogen_core/_closure_agent.py
autogen_core/_component_config.py
autogen_core/_constants.py
autogen_core/_default_subscription.py
autogen_core/_default_topic.py
autogen_core/_function_utils.py
autogen_core/_image.py
autogen_core/_intervention.py
autogen_core/_message_context.py
autogen_core/_message_handler_context.py
autogen_core/_queue.py
autogen_core/_routed_agent.py
autogen_core/_runtime_impl_helpers.py
autogen_core/_serialization.py
autogen_core/_single_threaded_agent_runtime.py
autogen_core/_subscription.py
autogen_core/_subscription_context.py
autogen_core/_topic.py
autogen_core/_type_helpers.py
autogen_core/_type_prefix_subscription.py
autogen_core/_type_subscription.py
autogen_core/_types.py
autogen_core/exceptions.py
autogen_core/logging.py
autogen_core/py.typed
autogen_core/_telemetry/__init__.py
autogen_core/_telemetry/_constants.py
autogen_core/_telemetry/_genai.py
autogen_core/_telemetry/_propagation.py
autogen_core/_telemetry/_tracing.py
autogen_core/_telemetry/_tracing_config.py
autogen_core/code_executor/__init__.py
autogen_core/code_executor/_base.py
autogen_core/code_executor/_func_with_reqs.py
autogen_core/memory/__init__.py
autogen_core/memory/_base_memory.py
autogen_core/memory/_list_memory.py
autogen_core/model_context/__init__.py
autogen_core/model_context/_buffered_chat_completion_context.py
autogen_core/model_context/_chat_completion_context.py
autogen_core/model_context/_head_and_tail_chat_completion_context.py
autogen_core/model_context/_token_limited_chat_completion_context.py
autogen_core/model_context/_unbounded_chat_completion_context.py
autogen_core/models/__init__.py
autogen_core/models/_model_client.py
autogen_core-0.7.3.dist-info/METADATA
autogen_core-0.7.3.dist-info/WHEEL
autogen_core-0.7.3.dist-info/licenses/LICENSE-CODE
autogen_core-0.7.3.dist-info/RECORD
