Metadata-Version: 2.4
Name: autogen-core
Version: 0.7.3
Summary: Foundational interfaces and agent runtime implementation for AutoGen
License:     MIT License
License-File: LICENSE-CODE
Classifier: License :: OSI Approved :: MIT License
Classifier: Operating System :: OS Independent
Classifier: Programming Language :: Python :: 3
Requires-Python: >=3.10
Requires-Dist: jsonref~=1.1.0
Requires-Dist: opentelemetry-api>=1.34.1
Requires-Dist: pillow>=11.0.0
Requires-Dist: protobuf~=5.29.3
Requires-Dist: pydantic<3.0.0,>=2.10.0
Requires-Dist: typing-extensions>=4.0.0
